README.rst
setup.py
manipulator/__init__.py
manipulator/get.py
manipulator/query.py
manipulator/update.py
manipulator.egg-info/PKG-INFO
manipulator.egg-info/SOURCES.txt
manipulator.egg-info/dependency_links.txt
manipulator.egg-info/top_level.txt