Metadata-Version: 1.1
Name: manipulator
Version: 0.0.2
Summary: Python data manipulation made braindead
Home-page: https://github.com/hellerve/manipulator
Author: Veit Heller
Author-email: veit@veitheller.de
License: MIT License
Download-URL: https://github.com/hellerve/hawkweed/tarball/0.0.2
Platform: UNKNOWN
